{
  "id": "MAP_NAVEL_ROCK_FORK",
  "name": "NavelRock_Fork",
  "layout": "LAYOUT_NAVEL_ROCK_FORK",
  "music": "MUS_HG_RUINS_OF_ALPH",
  "region_map_section": "MAPSEC_NAVEL_ROCK",
  "requires_flash": true,
  "weather": "WEATHER_NONE",
  "map_type": "MAP_TYPE_UNDERGROUND",
  "allow_cycling": true,
  "allow_escaping": true,
  "allow_running": true,
  "show_map_name": true,
  "battle_scene": "MAP_BATTLE_SCENE_NORMAL",
  "connections": 0,
  "object_events": [

  ],
  "warp_events": [
    {
      "x": 11,
      "y": 79,
      "elevation": 3,
      "dest_map": "MAP_NAVEL_ROCK_B1F",
      "dest_warp_id": "1"
    },
    {
      "x": 13,
      "y": 4,
      "elevation": 0,
      "dest_map": "MAP_NAVEL_ROCK_UNOWN_CHAMBER",
      "dest_warp_id": "0"
    },
    {
      "x": 16,
      "y": 60,
      "elevation": 0,
      "dest_map": "MAP_NAVEL_ROCK_FORK",
      "dest_warp_id": "5"
    },
    {
      "x": 25,
      "y": 72,
      "elevation": 0,
      "dest_map": "MAP_NAVEL_ROCK_FORK",
      "dest_warp_id": "4"
    },
    {
      "x": 20,
      "y": 73,
      "elevation": 0,
      "dest_map": "MAP_NAVEL_ROCK_FORK",
      "dest_warp_id": "7"
    },
    {
      "x": 11,
      "y": 61,
      "elevation": 0,
      "dest_map": "MAP_NAVEL_ROCK_FORK",
      "dest_warp_id": "6"
    }
  ],
  "coord_events": [

  ],
  "bg_events": [
    {
      "type": "sign",
      "x": 24,
      "y": 15,
      "elevation": 0,
      "player_facing_dir": "BG_EVENT_PLAYER_FACING_ANY",
      "script": "NavelRock_Fork_Puzzle_Kabuto"
    },
    {
      "type": "sign",
      "x": 24,
      "y": 42,
      "elevation": 0,
      "player_facing_dir": "BG_EVENT_PLAYER_FACING_ANY",
      "script": "NavelRock_Fork_Puzzle_Ho_Oh"
    },
    {
      "type": "sign",
      "x": 2,
      "y": 58,
      "elevation": 0,
      "player_facing_dir": "BG_EVENT_PLAYER_FACING_ANY",
      "script": "NavelRock_Fork_Puzzle_Aerodactyl"
    },
    {
      "type": "sign",
      "x": 2,
      "y": 15,
      "elevation": 0,
      "player_facing_dir": "BG_EVENT_PLAYER_FACING_ANY",
      "script": "NavelRock_Fork_Puzzle_Omanyte"
    }
  ]
}
